toyrobot/__init__.py
toyrobot/_nbdev.py
toyrobot/core.py
toyrobot/direction.py
toyrobot/main.py
toyrobot/robot.py
toyrobot/test.py
toyrobot-0.0.16.dist-info/LICENSE
toyrobot-0.0.16.dist-info/METADATA
toyrobot-0.0.16.dist-info/WHEEL
toyrobot-0.0.16.dist-info/entry_points.txt
toyrobot-0.0.16.dist-info/top_level.txt
toyrobot-0.0.16.dist-info/RECORD
