Metadata-Version: 2.1
Name: toyrobot
Version: 0.0.16
Summary: A toy project to make a toy robot.
Home-page: https://github.com/amaarora/toyrobot/tree/master/
Author: Aman Arora
Author-email: aman.arora0210@gmail.com
License: Apache Software License 2.0
Keywords: python,OOPS
Platform: UNKNOWN
Classifier: Development Status :: 3 - Alpha
Classifier: Intended Audience :: Developers
Classifier: License :: OSI Approved :: Apache Software License
Classifier: Natural Language :: English
Classifier: Programming Language :: Python :: 3.6
Classifier: Programming Language :: Python :: 3.7
Classifier: Programming Language :: Python :: 3.8
Requires-Python: >=3.6
Requires-Dist: nbdev (>0.2.17)
